<?xml version='1.0' encoding='UTF-8'?>
<odoo>
  <record id="studio_customization.n8n_group_system_7c31b723-96e9-4563-8ed3-554b60a25a72" model="ir.model.access" context="{'studio': True}">
    <field name="active" eval="True"/>
    <field name="group_id" ref="base.group_system"/>
    <field name="model_id" ref="studio_customization.n8n_331486a6-3276-4696-a1de-81698b8255d7"/>
    <field name="name">n8n group_system</field>
    <field name="perm_create" eval="True"/>
    <field name="perm_read" eval="True"/>
    <field name="perm_unlink" eval="True"/>
    <field name="perm_write" eval="True"/>
  </record>
  <record id="studio_customization.n8n_group_user_a362dad4-ae2c-4023-b5bc-0b0362820e21" model="ir.model.access" context="{'studio': True}">
    <field name="active" eval="True"/>
    <field name="group_id" ref="base.group_user"/>
    <field name="model_id" ref="studio_customization.n8n_331486a6-3276-4696-a1de-81698b8255d7"/>
    <field name="name">n8n group_user</field>
    <field name="perm_create" eval="True"/>
    <field name="perm_read" eval="True"/>
    <field name="perm_unlink" eval="False"/>
    <field name="perm_write" eval="True"/>
  </record>
  <record id="studio_customization.pending_category_fet_52b7856d-0440-43fa-9489-c2812c921099" model="ir.model.access" context="{'studio': True}">
    <field name="active" eval="True"/>
    <field name="group_id" ref="base.group_system"/>
    <field name="model_id" ref="studio_customization.pending_category_fet_33880052-7f6d-4e72-ab91-217e33b332af"/>
    <field name="name">Pending category fetcher group_system</field>
    <field name="perm_create" eval="True"/>
    <field name="perm_read" eval="True"/>
    <field name="perm_unlink" eval="True"/>
    <field name="perm_write" eval="True"/>
  </record>
  <record id="studio_customization.pending_category_fet_c83c62be-1ac7-4ea8-bf22-f0bbb58073fd" model="ir.model.access" context="{'studio': True}">
    <field name="active" eval="True"/>
    <field name="group_id" ref="base.group_user"/>
    <field name="model_id" ref="studio_customization.pending_category_fet_33880052-7f6d-4e72-ab91-217e33b332af"/>
    <field name="name">Pending category fetcher group_user</field>
    <field name="perm_create" eval="True"/>
    <field name="perm_read" eval="True"/>
    <field name="perm_unlink" eval="False"/>
    <field name="perm_write" eval="True"/>
  </record>
  <record id="studio_customization.pending_products_fet_5988e616-d401-4449-8a15-53a906ae2ba3" model="ir.model.access" context="{'studio': True}">
    <field name="active" eval="True"/>
    <field name="group_id" ref="base.group_system"/>
    <field name="model_id" ref="studio_customization.pending_products_fet_92c68fca-8bc3-4e11-a9da-790479c232f7"/>
    <field name="name">Pending products fetcher group_system</field>
    <field name="perm_create" eval="True"/>
    <field name="perm_read" eval="True"/>
    <field name="perm_unlink" eval="True"/>
    <field name="perm_write" eval="True"/>
  </record>
  <record id="studio_customization.pending_products_fet_93b2b666-f420-498f-b63b-bb919d1f9b19" model="ir.model.access" context="{'studio': True}">
    <field name="active" eval="True"/>
    <field name="group_id" ref="base.group_user"/>
    <field name="model_id" ref="studio_customization.pending_products_fet_92c68fca-8bc3-4e11-a9da-790479c232f7"/>
    <field name="name">Pending products fetcher group_user</field>
    <field name="perm_create" eval="True"/>
    <field name="perm_read" eval="True"/>
    <field name="perm_unlink" eval="False"/>
    <field name="perm_write" eval="True"/>
  </record>
</odoo>
